_flashair_sync
