Metadata-Version: 1.1
Name: flashair-sync
Version: 0.1.0
Summary: Simple directory syncer for Toshiba Flashair SD cards (used in 3D printers).
Home-page: https://github.com/vindolin/flashair_sync
Author: Thomas Schüßler
Author-email: vindolin@gmail.com
License: MIT
Keywords: 3d printing,flashair,sync
Platform: UNKNOWN
Classifier: Development Status :: 4 - Beta
